ssepy/__init__.py
ssepy/model_performance_evaluator.py
ssepy/oracle_estimator.py
ssepy-0.1.1.dist-info/LICENSE
ssepy-0.1.1.dist-info/METADATA
ssepy-0.1.1.dist-info/NOTICE
ssepy-0.1.1.dist-info/WHEEL
ssepy-0.1.1.dist-info/RECORD
