Metadata-Version: 2.3
Name: ssepy
Version: 0.1.1
Summary: This package helps you stratify, sample, and estimate.
Author: Riccardo Fogliato
Requires-Python: >=3.9,<4.0
Classifier: Programming Language :: Python :: 3
Classifier: Programming Language :: Python :: 3.9
Classifier: Programming Language :: Python :: 3.10
Classifier: Programming Language :: Python :: 3.11
Classifier: Programming Language :: Python :: 3.12
Classifier: Programming Language :: Python :: 3.13
Requires-Dist: numpy (>=1.25.2,<2.0.0)
Requires-Dist: sphinx (>=7.3.7,<8.0.0)
